agentic_kit_flow/__init__.py
agentic_kit_flow/pattern/__init__.py
agentic_kit_flow/pattern/schema.py
agentic_kit_flow/pattern/component/__init__.py
agentic_kit_flow/pattern/component/executor/__init__.py
agentic_kit_flow/pattern/component/executor/base.py
agentic_kit_flow/pattern/component/executor/schema.py
agentic_kit_flow/pattern/component/executor/sequence_executor.py
agentic_kit_flow/pattern/component/executor/step_executor.py
agentic_kit_flow/pattern/component/planner/__init__.py
agentic_kit_flow/pattern/component/planner/base.py
agentic_kit_flow/pattern/component/planner/common_planner.py
agentic_kit_flow/pattern/component/planner/cot_planner.py
agentic_kit_flow/pattern/component/planner/cot_replanner.py
agentic_kit_flow/pattern/component/planner/dag_planner.py
agentic_kit_flow/pattern/component/planner/dag_replanner.py
agentic_kit_flow/pattern/component/planner/first_step_planner.py
agentic_kit_flow/pattern/component/planner/parser.py
agentic_kit_flow/pattern/component/planner/schema.py
agentic_kit_flow/pattern/component/planner/sequence_planner.py
agentic_kit_flow/pattern/component/resolver/__init__.py
agentic_kit_flow/pattern/component/resolver/base.py
agentic_kit_flow/pattern/component/resolver/schema.py
agentic_kit_flow/pattern/component/resolver/summary_resolver.py
agentic_kit_flow/pattern/component/tool_call/__init__.py
agentic_kit_flow/pattern/component/tool_call/schema.py
agentic_kit_flow/pattern/component/tool_call/tool_call_component.py
agentic_kit_flow/pattern/component/utils/__init__.py
agentic_kit_flow/pattern/component/utils/tool_call.py
agentic_kit_flow/pattern/llm_call/__init__.py
agentic_kit_flow/pattern/llm_call/llm_call_graph.py
agentic_kit_flow/pattern/llm_call/schema.py
agentic_kit_flow/pattern/plan_execute/__init__.py
agentic_kit_flow/pattern/plan_execute/base.py
agentic_kit_flow/pattern/plan_execute/cot_plan_execute.py
agentic_kit_flow/pattern/plan_execute/dag_plan_execute.py
agentic_kit_flow/pattern/plan_execute/schema.py
agentic_kit_flow-0.0.5.dist-info/METADATA
agentic_kit_flow-0.0.5.dist-info/WHEEL
agentic_kit_flow-0.0.5.dist-info/top_level.txt
agentic_kit_flow-0.0.5.dist-info/RECORD
