Metadata-Version: 2.1
Name: agentic-kit-flow
Version: 0.0.5
Summary: About agent flow&pattern based on Langgraph
Home-page: 
Author: manson
Author-email: manson.li3307@gmail.com
Keywords: AI,LLM,Agent
Classifier: Development Status :: 4 - Beta
Classifier: Intended Audience :: Developers
Classifier: Topic :: Scientific/Engineering :: Artificial Intelligence
Classifier: Programming Language :: Python :: 3
Classifier: License :: OSI Approved :: Apache Software License
Classifier: Operating System :: OS Independent
Requires-Python: >=3.10
Requires-Dist: agentic-kit-core
Requires-Dist: langchain-community
Requires-Dist: langchain-core
Requires-Dist: langgraph
Requires-Dist: pydantic
Requires-Dist: python-redis-lock
Requires-Dist: setuptools
Requires-Dist: starlette
Requires-Dist: typing-extensions
Requires-Dist: websocket-client
